odoo/addons/project_deadline/README.rst
odoo/addons/project_deadline/__init__.py
odoo/addons/project_deadline/__manifest__.py
odoo/addons/project_deadline/i18n/de.po
odoo/addons/project_deadline/i18n/es.po
odoo/addons/project_deadline/i18n/es_AR.po
odoo/addons/project_deadline/i18n/fi.po
odoo/addons/project_deadline/i18n/fr.po
odoo/addons/project_deadline/i18n/fr_FR.po
odoo/addons/project_deadline/i18n/hr.po
odoo/addons/project_deadline/i18n/it.po
odoo/addons/project_deadline/i18n/project_deadline.pot
odoo/addons/project_deadline/i18n/sl.po
odoo/addons/project_deadline/i18n/sv.po
odoo/addons/project_deadline/models/__init__.py
odoo/addons/project_deadline/models/project_project.py
odoo/addons/project_deadline/models/project_task.py
odoo/addons/project_deadline/readme/CONTRIBUTORS.rst
odoo/addons/project_deadline/readme/DESCRIPTION.rst
odoo/addons/project_deadline/readme/USAGE.rst
odoo/addons/project_deadline/static/description/icon.png
odoo/addons/project_deadline/static/description/index.html
odoo/addons/project_deadline/tests/__init__.py
odoo/addons/project_deadline/tests/test_project_deadline.py
odoo/addons/project_deadline/views/project_project_view.xml
odoo/addons/project_deadline/views/project_task_view.xml
odoo14_addon_project_deadline-14.0.1.0.1.dev25.dist-info/METADATA
odoo14_addon_project_deadline-14.0.1.0.1.dev25.dist-info/WHEEL
odoo14_addon_project_deadline-14.0.1.0.1.dev25.dist-info/top_level.txt
odoo14_addon_project_deadline-14.0.1.0.1.dev25.dist-info/RECORD
